README
setup.py
src/baseboard/__init__.py
src/baseboard/admin.py
src/baseboard/helpers.py
src/baseboard/mocks.py
src/baseboard/models.py
src/baseboard/runtests.py
src/baseboard/tests.py
src/baseboard/testsettings.py
src/baseboard/urls.py
src/baseboard/management/__init__.py
src/baseboard/management/commands/__init__.py
src/baseboard/management/commands/update_baseboard_feeds.py
src/baseboard/management/commands/update_baseboard_summaries.py
src/django_baseboard.egg-info/PKG-INFO
src/django_baseboard.egg-info/SOURCES.txt
src/django_baseboard.egg-info/dependency_links.txt
src/django_baseboard.egg-info/requires.txt
src/django_baseboard.egg-info/top_level.txt