Metadata-Version: 1.0
Name: django-baseboard
Version: 0.3
Summary: Dashboard view across various Basecamp projects, powered by Django
Home-page: http://github.com/cmheisel/django-baseboard
Author: Chris Heisel
Author-email: chris@heisel.org
License: MIT
Platform: UNKNOWN
Classifier: Development Status :: 4 - Beta
Classifier: Framework :: Django
Classifier: Intended Audience :: Developers
Classifier: License :: OSI Approved :: MIT License
Classifier: Natural Language :: English
Classifier: Programming Language :: Python
Classifier: Topic :: Internet :: WWW/HTTP
Classifier: Topic :: Office/Business :: Groupware
Classifier: Topic :: Office/Business :: Scheduling
Classifier: Topic :: Software Development :: Libraries :: Python Modules
